zentuxlog_client
