Metadata-Version: 2.1
Name: zentuxlog-client
Version: 1.0.3
Summary: Sonde / Client API ZentuxLog
Home-page: https://gitlab.django-creation.net/zentux/zentuxlog-client
Author: ZENTUX SAS
Author-email: contact@zentux.fr
License: Apache License 2.0
Keywords: zentuxlog development client
Platform: UNKNOWN
Classifier: Development Status :: 3 - Alpha
Classifier: Intended Audience :: Developers
Classifier: License :: OSI Approved :: Apache Software License
Classifier: Programming Language :: Python
Classifier: Programming Language :: Python :: 3 :: Only
Classifier: Programming Language :: Python :: 3.5
Classifier: Programming Language :: Python :: 3.6
Classifier: Programming Language :: Python :: 3.7
Classifier: Environment :: Web Environment
